{
    "mainTitle": "מחירים נוחים",
    "text": "הצעת מחיר לדוגמה עבור עסק עם:",
    "businessDetailsTitle": "פרטי עסק",
    "businessDetailsList": [
        {
            "title": "מחזור שנתי",
            "number": "800000",
            "currency": "&#8362;"
        },
        {
            "title": "לקוחות",
            "number": "12",
            "currency": "&#8362;"
        },
        {
            "title": "מחזור שנתי",
            "number": "600000",
            "currency": "&#8362;"
        }
    ],
    "offerPriceTitle": "הצעת מחיר",
    "offerList": [
        {
            "title":"תשלום חודשי",
            "number":"3000",
            "currency": "&#8362;",
            "text":"שהם 0.34% מסך החובות הפתוחים לאותו החודש"
        },
        {
            "title":"תשלום שנתי",
            "number":"200",
            "currency": "&#8362;",
            "text":"100 ש”ח עבור כל לקוח החל מהלקוח ה- 10"
        },
        {
            "title":"תשלום חודשי",
            "number":"6",
            "currency": "%",
            "text":"שהם 0.34% מסך החובות הפתוחים לאותו החודש",
            "imgUrl":"assets/img/present.png"
        },
        {
            "title":"תשלום חודשי",
            "number":"2000",
            "currency": "&#8362;",
            "text":"שהם 0.34% מסך החובות הפתוחים לאותו החודש"
        },
        {
            "title":"תשלום שנתי",
            "number":"200",
            "currency": "&#8362;",
            "text":"100 ש”ח עבור כל לקוח החל מהלקוח ה- 10"
        }
    ],
    "header": {
        "logoUrl": "assets/img/logo.png",
        "headerLinks": {
            "faqLinkText": "שאלות ותשובות",
            "contactLinkText": "צור קשר",
            "aboutLinkText": "אודות כלל ביטוח אשראי"
        },
        "polisaBtn": {
            "text": "לאתר ניהול הפוליסה",
            "linkUrl": "https://www.clalbit.co.il/",
            "targetBlank": false,
            "isInternal": false
        }
    }
}