[
    {
        "mainTitle": "לעבוד בראש שקט<br>עם ביטוח אשראי מבית כלל",
        "text": "לראשונה בישראל, שירותי ביטוח אשראי של כלל ניתנים גם לעסקים בינוניים וקטנים,בעלי מחזור הכנסות שנתי שבין 10-50 מיליון שח ביטוח אשראי מאפשר לך לבצע יותר עסקאות בצורה בטוחה,ומקנה ייתרון במימון הבנקאי כל זאת עם גב של חברת כלל ביטוח",
        "linkReadMore": "",
        "linkText": "יצאונים? זקוקים לביטוח פרויקטלי?",
        "link": "www",
        "note": "כלל ממשיכה לספק ביטוח מימון פרויקטלי, ביטוח הזמנות ומגוון ביטוחים נוספים המתאימים לעסקים המובילים בשוק"
    },
    {
        "mainTitle": "המבוטחים שלנו ישנים <br>טוב יותר בלילה",
        "text": "ביטוח אשראי מאפשר לך לעבוד בראש שקט ובביטחון גם אם יש לך<br> כמה עסקאות שאתה לא לגמרי בטוח אם תראה את הכסף מהם",
        "linkReadMore": "https://www.google.com/",
        "linkText": "",
        "link": "",
        "note": ""
    },
    {
        "mainTitle": "פנה מקום ביומן,עוד כ-20 <br>עסקאות שנתית בדרך אליך",
        "text": "כשהכסף שלך בטוח, תוכל לעבוד עם אותם לקוחות שפעם היית מפחד לקחת לראשונה בישראל שירותי ביטוח אשראי של כלל ניתנים גם לעסקים בעלי מחזור הכנסות שנתי של בין 5 ל-10 מליון ש",
        "linkReadMore": "https://www.youtube.com",
        "linkText": "",
        "link": "",
        "note": ""
    }
]